src/mcp_server_headless_gmail/__init__.py
src/mcp_server_headless_gmail/server.py
orange_mcp_server_headless_gmail-0.1.0.dist-info/METADATA
orange_mcp_server_headless_gmail-0.1.0.dist-info/WHEEL
orange_mcp_server_headless_gmail-0.1.0.dist-info/entry_points.txt
orange_mcp_server_headless_gmail-0.1.0.dist-info/licenses/LICENSE
orange_mcp_server_headless_gmail-0.1.0.dist-info/RECORD
