Metadata-Version: 2.4
Name: orange-mcp-server-headless-gmail
Version: 0.1.0
Summary: A simple Gmail MCP server
License-File: LICENSE
Requires-Python: >=3.10
Requires-Dist: google-api-python-client>=2.127.0
Requires-Dist: google-auth-httplib2>=0.2.0
Requires-Dist: google-auth-oauthlib>=1.2.0
Requires-Dist: google-auth>=2.34.0
Requires-Dist: mcp>=1.4.1
Requires-Dist: python-dateutil>=2.8.2
Requires-Dist: python-dotenv>=1.0.1
